mcp_server_spidy/__init__.py
mcp_server_spidy/server.py
mcp_server_spidy/test_server.py
mcp_server_spidy-0.1.2.dist-info/METADATA
mcp_server_spidy-0.1.2.dist-info/WHEEL
mcp_server_spidy-0.1.2.dist-info/entry_points.txt
mcp_server_spidy-0.1.2.dist-info/RECORD
