Metadata-Version: 2.3
Name: mcp-server-spidy
Version: 0.1.2
Summary: a web cralwer for claude mcp
Author-email: Jose Roberts <webterpr@gmail.com>
Requires-Python: >=3.10
Requires-Dist: aiohttp>=3.11.10
Requires-Dist: mcp>=1.1.1
